klaviyo_for_django/__init__.py
klaviyo_for_django-0.0.4.dist-info/LICENSE
klaviyo_for_django-0.0.4.dist-info/METADATA
klaviyo_for_django-0.0.4.dist-info/WHEEL
klaviyo_for_django-0.0.4.dist-info/top_level.txt
klaviyo_for_django-0.0.4.dist-info/RECORD
