Metadata-Version: 2.1
Name: klaviyo-for-django
Version: 0.0.4
Home-page: http://pypi.python.org/pypi/klaviyo-for-django/
Author: Santiago Fernandez
Author-email: 
License: MIT
License-File: LICENSE
Requires-Dist: Django (>=4.0.0)
Requires-Dist: pytest
Requires-Dist: klaviyo-api
